npimage/__init__.py
npimage/binary.py
npimage/filters.py
npimage/label.py
npimage/measures.py
npimage-0.1.dist-info/LICENSE
npimage-0.1.dist-info/METADATA
npimage-0.1.dist-info/WHEEL
npimage-0.1.dist-info/top_level.txt
npimage-0.1.dist-info/RECORD
