Metadata-Version: 2.1
Name: npimage
Version: 0.1
Summary: ndimage in numpy
Home-page: https://github.com/Image-Py/npimage
Author: YXDragon
Author-email: yxdragon@imagepy.org
License: BSD 3-clause
Platform: UNKNOWN
Requires-Dist: numpy
